{
  "run_id": "20260217T143132Z",
  "generated_at": "2026-02-17T14:31:36.757949+00:00",
  "training_goal": "3-specialty node-fleet co-training",
  "specialties": [
    "code_execute",
    "doc_plan",
    "memory_storage"
  ],
  "constants_file": "training/config/node_fleet_constants.json",
  "spin_formula": "((context - non_interest) + interest + relevancy) + k_ternary*ternary_flux - k_drift*hyperbolic_drift + k_memory*memory_retention + k_coherence*consensus_coherence + k_harmonic*harmonic_wall_signal",
  "data": {
    "sample_count": 3403,
    "train_count": 2722,
    "val_count": 681,
    "embedding_dim": 320,
    "sources_used": [
      "training\\ingest\\docs_20260217T143127Z.jsonl"
    ],
    "conversation_spin_gist": "c38b2eface8d456b90c6bf02678871d8"
  },
  "specialist_models": {
    "code_execute": {
      "weights_shape": [
        2,
        320
      ],
      "history": [
        {
          "epoch": 1.0,
          "learning_rate": 0.16,
          "train_loss": 0.6920621395111084,
          "train_accuracy": 0.5844966769218445,
          "val_loss": 0.6873238682746887,
          "val_accuracy": 0.7077826857566833
        },
        {
          "epoch": 2.0,
          "learning_rate": 0.1552,
          "train_loss": 0.6872578263282776,
          "train_accuracy": 0.7119764685630798,
          "val_loss": 0.6827753782272339,
          "val_accuracy": 0.7312775254249573
        },
        {
          "epoch": 3.0,
          "learning_rate": 0.15054399999999998,
          "train_loss": 0.6827873587608337,
          "train_accuracy": 0.7369581460952759,
          "val_loss": 0.6785367727279663,
          "val_accuracy": 0.7474302649497986
        },
        {
          "epoch": 4.0,
          "learning_rate": 0.14602768,
          "train_loss": 0.6786219477653503,
          "train_accuracy": 0.7432035207748413,
          "val_loss": 0.67458176612854,
          "val_accuracy": 0.7474302649497986
        },
        {
          "epoch": 5.0,
          "learning_rate": 0.14164684959999999,
          "train_loss": 0.6747357845306396,
          "train_accuracy": 0.7457751631736755,
          "val_loss": 0.6708868145942688,
          "val_accuracy": 0.7518355250358582
        },
        {
          "epoch": 6.0,
          "learning_rate": 0.137397444112,
          "train_loss": 0.6711056232452393,
          "train_accuracy": 0.7450404167175293,
          "val_loss": 0.6674305200576782,
          "val_accuracy": 0.7547723650932312
        },
        {
          "epoch": 7.0,
          "learning_rate": 0.13327552078863997,
          "train_loss": 0.6677102446556091,
          "train_accuracy": 0.7446730136871338,
          "val_loss": 0.6641936302185059,
          "val_accuracy": 0.7547723650932312
        },
        {
          "epoch": 8.0,
          "learning_rate": 0.12927725516498076,
          "train_loss": 0.664530873298645,
          "train_accuracy": 0.7450404167175293,
          "val_loss": 0.6611586809158325,
          "val_accuracy": 0.7547723650932312
        },
        {
          "epoch": 9.0,
          "learning_rate": 0.12539893751003134,
          "train_loss": 0.6615501642227173,
          "train_accuracy": 0.7446730136871338,
          "val_loss": 0.6583099365234375,
          "val_accuracy": 0.757709264755249
        },
        {
          "epoch": 10.0,
          "learning_rate": 0.12163696938473041,
          "train_loss": 0.6587526202201843,
          "train_accuracy": 0.7443056702613831,
          "val_loss": 0.6556330323219299,
          "val_accuracy": 0.7606461048126221
        },
        {
          "epoch": 11.0,
          "learning_rate": 0.1179878603031885,
          "train_loss": 0.6561241745948792,
          "train_accuracy": 0.7439382672309875,
          "val_loss": 0.653114914894104,
          "val_accuracy": 0.7606461048126221
        },
        {
          "epoch": 12.0,
          "learning_rate": 0.11444822449409284,
          "train_loss": 0.6536518335342407,
          "train_accuracy": 0.7435709238052368,
          "val_loss": 0.6507437825202942,
          "val_accuracy": 0.7606461048126221
        },
        {
          "epoch": 13.0,
          "learning_rate": 0.11101477775927004,
          "train_loss": 0.6513241529464722,
          "train_accuracy": 0.7432035207748413,
          "val_loss": 0.6485089063644409,
          "val_accuracy": 0.7606461048126221
        },
        {
          "epoch": 14.0,
          "learning_rate": 0.10768433442649195,
          "train_loss": 0.6491303443908691,
          "train_accuracy": 0.7439382672309875,
          "val_loss": 0.6464003324508667,
          "val_accuracy": 0.7606461048126221
        },
        {
          "epoch": 15.0,
          "learning_rate": 0.10445380439369718,
          "train_loss": 0.647060751914978,
          "train_accuracy": 0.7443056702613831,
          "val_loss": 0.6444091796875,
          "val_accuracy": 0.7606461048126221
        },
        {
          "epoch": 16.0,
          "learning_rate": 0.10132019026188627,
          "train_loss": 0.6451066732406616,
          "train_accuracy": 0.7446730136871338,
          "val_loss": 0.642527163028717,
          "val_accuracy": 0.7621145248413086
        },
        {
          "epoch": 17.0,
          "learning_rate": 0.09828058455402967,
          "train_loss": 0.6432598829269409,
          "train_accuracy": 0.7450404167175293,
          "val_loss": 0.6407468318939209,
          "val_accuracy": 0.7621145248413086
        },
        {
          "epoch": 18.0,
          "learning_rate": 0.09533216701740878,
          "train_loss": 0.641512930393219,
          "train_accuracy": 0.7450404167175293,
          "val_loss": 0.6390612721443176,
          "val_accuracy": 0.7635829448699951
        },
        {
          "epoch": 19.0,
          "learning_rate": 0.09247220200688652,
          "train_loss": 0.6398591995239258,
          "train_accuracy": 0.74540776014328,
          "val_loss": 0.637464165687561,
          "val_accuracy": 0.7635829448699951
        },
        {
          "epoch": 20.0,
          "learning_rate": 0.08969803594667992,
          "train_loss": 0.6382923722267151,
          "train_accuracy": 0.7450404167175293,
          "val_loss": 0.6359496712684631,
          "val_accuracy": 0.7635829448699951
        },
        {
          "epoch": 21.0,
          "learning_rate": 0.08700709486827952,
          "train_loss": 0.6368067264556885,
          "train_accuracy": 0.7443056702613831,
          "val_loss": 0.6345124244689941,
          "val_accuracy": 0.7635829448699951
        },
        {
          "epoch": 22.0,
          "learning_rate": 0.08439688202223114,
          "train_loss": 0.6353970170021057,
          "train_accuracy": 0.7443056702613831,
          "val_loss": 0.6331475973129272,
          "val_accuracy": 0.7635829448699951
        },
        {
          "epoch": 23.0,
          "learning_rate": 0.0818649755615642,
          "train_loss": 0.63405841588974,
          "train_accuracy": 0.7443056702613831,
          "val_loss": 0.6318504810333252,
          "val_accuracy": 0.7635829448699951
        },
        {
          "epoch": 24.0,
          "learning_rate": 0.07940902629471726,
          "train_loss": 0.6327863335609436,
          "train_accuracy": 0.7439382672309875,
          "val_loss": 0.6306170225143433,
          "val_accuracy": 0.7635829448699951
        }
      ],
      "growth": {
        "confirmed": true,
        "val_accuracy_gain": 0.0558,
        "val_loss_drop": 0.056707,
        "first_val_accuracy": 0.707783,
        "last_val_accuracy": 0.763583
      },
      "class_balance": {
        "train_positive_ratio": 0.73806,
        "val_positive_ratio": 0.763583
      }
    },
    "doc_plan": {
      "weights_shape": [
        2,
        320
      ],
      "history": [
        {
          "epoch": 1.0,
          "learning_rate": 0.16,
          "train_loss": 0.6946417093276978,
          "train_accuracy": 0.3916237950325012,
          "val_loss": 0.6914989948272705,
          "val_accuracy": 0.5888399481773376
        },
        {
          "epoch": 2.0,
          "learning_rate": 0.1552,
          "train_loss": 0.6914721131324768,
          "train_accuracy": 0.6164584755897522,
          "val_loss": 0.6888110637664795,
          "val_accuracy": 0.6431717872619629
        },
        {
          "epoch": 3.0,
          "learning_rate": 0.15054399999999998,
          "train_loss": 0.6885225176811218,
          "train_accuracy": 0.666054368019104,
          "val_loss": 0.6863120794296265,
          "val_accuracy": 0.6710719466209412
        },
        {
          "epoch": 4.0,
          "learning_rate": 0.14602768,
          "train_loss": 0.6857742667198181,
          "train_accuracy": 0.6748714447021484,
          "val_loss": 0.683985710144043,
          "val_accuracy": 0.6813509464263916
        },
        {
          "epoch": 5.0,
          "learning_rate": 0.14164684959999999,
          "train_loss": 0.6832101345062256,
          "train_accuracy": 0.6800146698951721,
          "val_loss": 0.6818171143531799,
          "val_accuracy": 0.6813509464263916
        },
        {
          "epoch": 6.0,
          "learning_rate": 0.137397444112,
          "train_loss": 0.6808149218559265,
          "train_accuracy": 0.6796473264694214,
          "val_loss": 0.6797932386398315,
          "val_accuracy": 0.6828193664550781
        },
        {
          "epoch": 7.0,
          "learning_rate": 0.13327552078863997,
          "train_loss": 0.6785746812820435,
          "train_accuracy": 0.6811168193817139,
          "val_loss": 0.6779021620750427,
          "val_accuracy": 0.685756266117096
        },
        {
          "epoch": 8.0,
          "learning_rate": 0.12927725516498076,
          "train_loss": 0.6764768958091736,
          "train_accuracy": 0.6800146698951721,
          "val_loss": 0.6761329174041748,
          "val_accuracy": 0.685756266117096
        },
        {
          "epoch": 9.0,
          "learning_rate": 0.12539893751003134,
          "train_loss": 0.6745104193687439,
          "train_accuracy": 0.6785451769828796,
          "val_loss": 0.6744759678840637,
          "val_accuracy": 0.685756266117096
        },
        {
          "epoch": 10.0,
          "learning_rate": 0.12163696938473041,
          "train_loss": 0.6726648211479187,
          "train_accuracy": 0.6767082810401917,
          "val_loss": 0.6729222536087036,
          "val_accuracy": 0.6842877864837646
        },
        {
          "epoch": 11.0,
          "learning_rate": 0.1179878603031885,
          "train_loss": 0.6709308624267578,
          "train_accuracy": 0.6763409376144409,
          "val_loss": 0.6714640855789185,
          "val_accuracy": 0.6842877864837646
        },
        {
          "epoch": 12.0,
          "learning_rate": 0.11444822449409284,
          "train_loss": 0.6693000793457031,
          "train_accuracy": 0.6763409376144409,
          "val_loss": 0.6700937747955322,
          "val_accuracy": 0.6828193664550781
        },
        {
          "epoch": 13.0,
          "learning_rate": 0.11101477775927004,
          "train_loss": 0.6677647829055786,
          "train_accuracy": 0.6763409376144409,
          "val_loss": 0.6688050627708435,
          "val_accuracy": 0.6828193664550781
        },
        {
          "epoch": 14.0,
          "learning_rate": 0.10768433442649195,
          "train_loss": 0.6663179993629456,
          "train_accuracy": 0.6759735345840454,
          "val_loss": 0.6675916910171509,
          "val_accuracy": 0.685756266117096
        },
        {
          "epoch": 15.0,
          "learning_rate": 0.10445380439369718,
          "train_loss": 0.664953351020813,
          "train_accuracy": 0.6756061911582947,
          "val_loss": 0.6664482355117798,
          "val_accuracy": 0.685756266117096
        },
        {
          "epoch": 16.0,
          "learning_rate": 0.10132019026188627,
          "train_loss": 0.6636649966239929,
          "train_accuracy": 0.6748714447021484,
          "val_loss": 0.6653698086738586,
          "val_accuracy": 0.685756266117096
        },
        {
          "epoch": 17.0,
          "learning_rate": 0.09828058455402967,
          "train_loss": 0.6624475121498108,
          "train_accuracy": 0.6741366386413574,
          "val_loss": 0.6643515229225159,
          "val_accuracy": 0.685756266117096
        },
        {
          "epoch": 18.0,
          "learning_rate": 0.09533216701740878,
          "train_loss": 0.6612960696220398,
          "train_accuracy": 0.6734018921852112,
          "val_loss": 0.6633894443511963,
          "val_accuracy": 0.6842877864837646
        },
        {
          "epoch": 19.0,
          "learning_rate": 0.09247220200688652,
          "train_loss": 0.6602061986923218,
          "train_accuracy": 0.6730345487594604,
          "val_loss": 0.6624796390533447,
          "val_accuracy": 0.6828193664550781
        },
        {
          "epoch": 20.0,
          "learning_rate": 0.08969803594667992,
          "train_loss": 0.6591737866401672,
          "train_accuracy": 0.6730345487594604,
          "val_loss": 0.6616185307502747,
          "val_accuracy": 0.6828193664550781
        },
        {
          "epoch": 21.0,
          "learning_rate": 0.08700709486827952,
          "train_loss": 0.6581950187683105,
          "train_accuracy": 0.6722998023033142,
          "val_loss": 0.6608029007911682,
          "val_accuracy": 0.6828193664550781
        },
        {
          "epoch": 22.0,
          "learning_rate": 0.08439688202223114,
          "train_loss": 0.6572664380073547,
          "train_accuracy": 0.6719323992729187,
          "val_loss": 0.6600297689437866,
          "val_accuracy": 0.6828193664550781
        },
        {
          "epoch": 23.0,
          "learning_rate": 0.0818649755615642,
          "train_loss": 0.6563848257064819,
          "train_accuracy": 0.6715649962425232,
          "val_loss": 0.6592963933944702,
          "val_accuracy": 0.6828193664550781
        },
        {
          "epoch": 24.0,
          "learning_rate": 0.07940902629471726,
          "train_loss": 0.6555472016334534,
          "train_accuracy": 0.6715649962425232,
          "val_loss": 0.6586002707481384,
          "val_accuracy": 0.6828193664550781
        }
      ],
      "growth": {
        "confirmed": true,
        "val_accuracy_gain": 0.093979,
        "val_loss_drop": 0.032899,
        "first_val_accuracy": 0.58884,
        "last_val_accuracy": 0.682819
      },
      "class_balance": {
        "train_positive_ratio": 0.664585,
        "val_positive_ratio": 0.684288
      }
    },
    "memory_storage": {
      "weights_shape": [
        2,
        320
      ],
      "history": [
        {
          "epoch": 1.0,
          "learning_rate": 0.16,
          "train_loss": 0.6944478750228882,
          "train_accuracy": 0.42358559370040894,
          "val_loss": 0.6934762001037598,
          "val_accuracy": 0.49339208006858826
        },
        {
          "epoch": 2.0,
          "learning_rate": 0.1552,
          "train_loss": 0.693261981010437,
          "train_accuracy": 0.5113886594772339,
          "val_loss": 0.6921975612640381,
          "val_accuracy": 0.5491923689842224
        },
        {
          "epoch": 3.0,
          "learning_rate": 0.15054399999999998,
          "train_loss": 0.6921528577804565,
          "train_accuracy": 0.5510653853416443,
          "val_loss": 0.6909984350204468,
          "val_accuracy": 0.5976505279541016
        },
        {
          "epoch": 4.0,
          "learning_rate": 0.14602768,
          "train_loss": 0.6911140084266663,
          "train_accuracy": 0.5859662294387817,
          "val_loss": 0.689872682094574,
          "val_accuracy": 0.6138032078742981
        },
        {
          "epoch": 5.0,
          "learning_rate": 0.14164684959999999,
          "train_loss": 0.6901398301124573,
          "train_accuracy": 0.5980896353721619,
          "val_loss": 0.6888143420219421,
          "val_accuracy": 0.6152716875076294
        },
        {
          "epoch": 6.0,
          "learning_rate": 0.137397444112,
          "train_loss": 0.6892251372337341,
          "train_accuracy": 0.6050698161125183,
          "val_loss": 0.6878184676170349,
          "val_accuracy": 0.6284875273704529
        },
        {
          "epoch": 7.0,
          "learning_rate": 0.13327552078863997,
          "train_loss": 0.6883652806282043,
          "train_accuracy": 0.6105804443359375,
          "val_loss": 0.6868801712989807,
          "val_accuracy": 0.6314243674278259
        },
        {
          "epoch": 8.0,
          "learning_rate": 0.12927725516498076,
          "train_loss": 0.6875560879707336,
          "train_accuracy": 0.6149889826774597,
          "val_loss": 0.6859952807426453,
          "val_accuracy": 0.6372981071472168
        },
        {
          "epoch": 9.0,
          "learning_rate": 0.12539893751003134,
          "train_loss": 0.6867936849594116,
          "train_accuracy": 0.6179279685020447,
          "val_loss": 0.6851599812507629,
          "val_accuracy": 0.6372981071472168
        },
        {
          "epoch": 10.0,
          "learning_rate": 0.12163696938473041,
          "train_loss": 0.6860745549201965,
          "train_accuracy": 0.6197648644447327,
          "val_loss": 0.6843706369400024,
          "val_accuracy": 0.6402349472045898
        },
        {
          "epoch": 11.0,
          "learning_rate": 0.1179878603031885,
          "train_loss": 0.6853956580162048,
          "train_accuracy": 0.6208670139312744,
          "val_loss": 0.6836240291595459,
          "val_accuracy": 0.6446402072906494
        },
        {
          "epoch": 12.0,
          "learning_rate": 0.11444822449409284,
          "train_loss": 0.6847540736198425,
          "train_accuracy": 0.6230712532997131,
          "val_loss": 0.6829172968864441,
          "val_accuracy": 0.6461086869239807
        },
        {
          "epoch": 13.0,
          "learning_rate": 0.11101477775927004,
          "train_loss": 0.6841471195220947,
          "train_accuracy": 0.6230712532997131,
          "val_loss": 0.6822476387023926,
          "val_accuracy": 0.6431717872619629
        },
        {
          "epoch": 14.0,
          "learning_rate": 0.10768433442649195,
          "train_loss": 0.6835724711418152,
          "train_accuracy": 0.6234386563301086,
          "val_loss": 0.6816126704216003,
          "val_accuracy": 0.6431717872619629
        },
        {
          "epoch": 15.0,
          "learning_rate": 0.10445380439369718,
          "train_loss": 0.6830278635025024,
          "train_accuracy": 0.6241734027862549,
          "val_loss": 0.6810100078582764,
          "val_accuracy": 0.6446402072906494
        },
        {
          "epoch": 16.0,
          "learning_rate": 0.10132019026188627,
          "train_loss": 0.6825114488601685,
          "train_accuracy": 0.6223365068435669,
          "val_loss": 0.6804376244544983,
          "val_accuracy": 0.6446402072906494
        },
        {
          "epoch": 17.0,
          "learning_rate": 0.09828058455402967,
          "train_loss": 0.6820211410522461,
          "train_accuracy": 0.6234386563301086,
          "val_loss": 0.6798935532569885,
          "val_accuracy": 0.6417033672332764
        },
        {
          "epoch": 18.0,
          "learning_rate": 0.09533216701740878,
          "train_loss": 0.6815553903579712,
          "train_accuracy": 0.6230712532997131,
          "val_loss": 0.6793761253356934,
          "val_accuracy": 0.6417033672332764
        },
        {
          "epoch": 19.0,
          "learning_rate": 0.09247220200688652,
          "train_loss": 0.6811127066612244,
          "train_accuracy": 0.6230712532997131,
          "val_loss": 0.6788835525512695,
          "val_accuracy": 0.6431717872619629
        },
        {
          "epoch": 20.0,
          "learning_rate": 0.08969803594667992,
          "train_loss": 0.6806914210319519,
          "train_accuracy": 0.6230712532997131,
          "val_loss": 0.6784144639968872,
          "val_accuracy": 0.6475771069526672
        },
        {
          "epoch": 21.0,
          "learning_rate": 0.08700709486827952,
          "train_loss": 0.6802904009819031,
          "train_accuracy": 0.6227039098739624,
          "val_loss": 0.6779673099517822,
          "val_accuracy": 0.6475771069526672
        },
        {
          "epoch": 22.0,
          "learning_rate": 0.08439688202223114,
          "train_loss": 0.6799083948135376,
          "train_accuracy": 0.6241734027862549,
          "val_loss": 0.6775409579277039,
          "val_accuracy": 0.6461086869239807
        },
        {
          "epoch": 23.0,
          "learning_rate": 0.0818649755615642,
          "train_loss": 0.67954421043396,
          "train_accuracy": 0.6245408058166504,
          "val_loss": 0.6771341562271118,
          "val_accuracy": 0.6475771069526672
        },
        {
          "epoch": 24.0,
          "learning_rate": 0.07940902629471726,
          "train_loss": 0.6791968941688538,
          "train_accuracy": 0.6249081492424011,
          "val_loss": 0.6767457127571106,
          "val_accuracy": 0.6490455269813538
        }
      ],
      "growth": {
        "confirmed": true,
        "val_accuracy_gain": 0.155653,
        "val_loss_drop": 0.01673,
        "first_val_accuracy": 0.493392,
        "last_val_accuracy": 0.649046
      },
      "class_balance": {
        "train_positive_ratio": 0.592579,
        "val_positive_ratio": 0.647577
      }
    }
  },
  "fleet_coordinator": {
    "weights": [
      0.020100299268960953,
      0.16311028599739075,
      0.06918790936470032
    ],
    "bias": 0.11642926031730709,
    "history": [
      {
        "epoch": 1.0,
        "learning_rate": 0.064,
        "train_loss": 0.6902561187744141,
        "train_accuracy": 0.6664217710494995,
        "val_loss": 0.6865652203559875,
        "val_accuracy": 0.6666666865348816
      },
      {
        "epoch": 2.0,
        "learning_rate": 0.0608,
        "train_loss": 0.6865907907485962,
        "train_accuracy": 0.6664217710494995,
        "val_loss": 0.6833154559135437,
        "val_accuracy": 0.6666666865348816
      },
      {
        "epoch": 3.0,
        "learning_rate": 0.05776,
        "train_loss": 0.6833509802818298,
        "train_accuracy": 0.6664217710494995,
        "val_loss": 0.6804320812225342,
        "val_accuracy": 0.6666666865348816
      },
      {
        "epoch": 4.0,
        "learning_rate": 0.054872,
        "train_loss": 0.6804765462875366,
        "train_accuracy": 0.6664217710494995,
        "val_loss": 0.6778648495674133,
        "val_accuracy": 0.6666666865348816
      },
      {
        "epoch": 5.0,
        "learning_rate": 0.05212839999999999,
        "train_loss": 0.6779173612594604,
        "train_accuracy": 0.6664217710494995,
        "val_loss": 0.6755713820457458,
        "val_accuracy": 0.6666666865348816
      },
      {
        "epoch": 6.0,
        "learning_rate": 0.049521979999999986,
        "train_loss": 0.6756312251091003,
        "train_accuracy": 0.6664217710494995,
        "val_loss": 0.6735159754753113,
        "val_accuracy": 0.6666666865348816
      },
      {
        "epoch": 7.0,
        "learning_rate": 0.04704588099999999,
        "train_loss": 0.6735824346542358,
        "train_accuracy": 0.6664217710494995,
        "val_loss": 0.6716683506965637,
        "val_accuracy": 0.6666666865348816
      },
      {
        "epoch": 8.0,
        "learning_rate": 0.04469358694999998,
        "train_loss": 0.6717408895492554,
        "train_accuracy": 0.6664217710494995,
        "val_loss": 0.6700027585029602,
        "val_accuracy": 0.6666666865348816
      },
      {
        "epoch": 9.0,
        "learning_rate": 0.042458907602499985,
        "train_loss": 0.6700809001922607,
        "train_accuracy": 0.6664217710494995,
        "val_loss": 0.6684972643852234,
        "val_accuracy": 0.6666666865348816
      },
      {
        "epoch": 10.0,
        "learning_rate": 0.04033596222237498,
        "train_loss": 0.6685804724693298,
        "train_accuracy": 0.6664217710494995,
        "val_loss": 0.6671329140663147,
        "val_accuracy": 0.6666666865348816
      },
      {
        "epoch": 11.0,
        "learning_rate": 0.038319164111256236,
        "train_loss": 0.6672207713127136,
        "train_accuracy": 0.6664217710494995,
        "val_loss": 0.6658933758735657,
        "val_accuracy": 0.6666666865348816
      },
      {
        "epoch": 12.0,
        "learning_rate": 0.03640320590569342,
        "train_loss": 0.665985643863678,
        "train_accuracy": 0.6664217710494995,
        "val_loss": 0.6647648811340332,
        "val_accuracy": 0.6666666865348816
      },
      {
        "epoch": 13.0,
        "learning_rate": 0.034583045610408744,
        "train_loss": 0.6648610234260559,
        "train_accuracy": 0.6664217710494995,
        "val_loss": 0.663735032081604,
        "val_accuracy": 0.6666666865348816
      },
      {
        "epoch": 14.0,
        "learning_rate": 0.032853893329888306,
        "train_loss": 0.6638349294662476,
        "train_accuracy": 0.6664217710494995,
        "val_loss": 0.6627933382987976,
        "val_accuracy": 0.6666666865348816
      },
      {
        "epoch": 15.0,
        "learning_rate": 0.03121119866339389,
        "train_loss": 0.6628965735435486,
        "train_accuracy": 0.6664217710494995,
        "val_loss": 0.6619305610656738,
        "val_accuracy": 0.6666666865348816
      },
      {
        "epoch": 16.0,
        "learning_rate": 0.029650638730224194,
        "train_loss": 0.6620369553565979,
        "train_accuracy": 0.6664217710494995,
        "val_loss": 0.6611385345458984,
        "val_accuracy": 0.6666666865348816
      },
      {
        "epoch": 17.0,
        "learning_rate": 0.028168106793712983,
        "train_loss": 0.6612479090690613,
        "train_accuracy": 0.6664217710494995,
        "val_loss": 0.6604103446006775,
        "val_accuracy": 0.6666666865348816
      },
      {
        "epoch": 18.0,
        "learning_rate": 0.026759701454027333,
        "train_loss": 0.6605223417282104,
        "train_accuracy": 0.6664217710494995,
        "val_loss": 0.6597395539283752,
        "val_accuracy": 0.6666666865348816
      },
      {
        "epoch": 19.0,
        "learning_rate": 0.025421716381325964,
        "train_loss": 0.6598541140556335,
        "train_accuracy": 0.6664217710494995,
        "val_loss": 0.6591207981109619,
        "val_accuracy": 0.6666666865348816
      },
      {
        "epoch": 20.0,
        "learning_rate": 0.024150630562259665,
        "train_loss": 0.6592377424240112,
        "train_accuracy": 0.6664217710494995,
        "val_loss": 0.6585490703582764,
        "val_accuracy": 0.6666666865348816
      },
      {
        "epoch": 21.0,
        "learning_rate": 0.02294309903414668,
        "train_loss": 0.6586681604385376,
        "train_accuracy": 0.6664217710494995,
        "val_loss": 0.6580201387405396,
        "val_accuracy": 0.6666666865348816
      },
      {
        "epoch": 22.0,
        "learning_rate": 0.021795944082439348,
        "train_loss": 0.6581412553787231,
        "train_accuracy": 0.6664217710494995,
        "val_loss": 0.6575301289558411,
        "val_accuracy": 0.6666666865348816
      },
      {
        "epoch": 23.0,
        "learning_rate": 0.020706146878317375,
        "train_loss": 0.6576530337333679,
        "train_accuracy": 0.6664217710494995,
        "val_loss": 0.6570755243301392,
        "val_accuracy": 0.6666666865348816
      },
      {
        "epoch": 24.0,
        "learning_rate": 0.019670839534401508,
        "train_loss": 0.657200276851654,
        "train_accuracy": 0.6664217710494995,
        "val_loss": 0.6566532850265503,
        "val_accuracy": 0.6666666865348816
      }
    ],
    "growth": {
      "confirmed": true,
      "val_accuracy_gain": 0.0,
      "val_loss_drop": 0.029912,
      "first_val_accuracy": 0.666667,
      "last_val_accuracy": 0.666667
    }
  },
  "growth": {
    "specialists_confirmed": true,
    "fleet_confirmed": true,
    "overall_confirmed": true
  },
  "huggingface_upload": {
    "status": "ok",
    "uploaded_files": [
      "node_fleet_runs/20260217T143132Z/fleet_training_metrics.json",
      "node_fleet_runs/20260217T143132Z/fleet_model.npz",
      "node_fleet_runs/20260217T143132Z/fleet_growth_summary.md"
    ]
  }
}