{
  "id": "8a5f80021b741e7e",
  "source": "internet_archive",
  "category": "quarantine/governance",
  "title": "CIA Reading Room cia-rdp87b01034r000200100035-5: PUBLIC LAW 91-596 91ST CONGRESS, S. 2193",
  "content": "# CIA Reading Room cia-rdp87b01034r000200100035-5: PUBLIC LAW 91-596 91ST CONGRESS, S. 2193\n\nCreator: CIA Reading Room\nDate: 1970-12-29T00:00:00Z\nDownloads: 83\nSubjects: CIA Reading Room\n\nAppro . for Relea gl9p%/N/R?_tQIA-RDP87j3O1O34ROOO2OO1OOO35-5 91st Congress, S. 2193 December 29, 1970 Rn act To assure safe and healthful working conditions for working men and women ; by authorizing enforcement of the standards developed under the Act; by assisting and encouraging the States in their efforts to assure safe and health- ful working conditions ; by providing for research, information, education, and training in the field of occupational safety and health ; and for other purposes. Be it enacted by the Senate and House of Representatives of the TJnited States of America in Congress assembled, That this Act may be cited as the \"Occupational Safety and Health Act of 1970\". SEC. (2) The Congress finds that personal injuries and illnesses aris- ing out of work situations impose a substantial burden upon, and are a hindrance to, interstate commerce in terms of lost production, wage loss, medical expenses, and disability compensation payments. (b) The Congress declares it to be its purpose and policy, through the exercise of its powers to regulate commerce. among the several States and with foreign nations and to provide for the general welfare, to, assure so far as possible every working man and woman in the Nation safe and healthful working conditions and to preserve our human resources- (1) by encouraging employers and employees in their efforts to reduce the number of occupational safety and health hazards at their places of employment, and to stimulate employers and employees to institute new and to perfect existing programs for providing safe and healthful working conditions; (2) by providing that employers and employees have separate but dependent responsibilities and rights with respect to achiev- ing safe and healthful working conditions; (3) by authorizing the Secretary of Labor to set mandatory occupational safety and health standards applicable to businesses affecting interstate commerce, and by creating an Occupational Safety and Health Review Commission for carrying out adjudi- catory functions under the Act; (4) by building upon advances already made through employer and employee initiative for providing safe and healthful working conditions ; (5) by providing for research in the field of occupational safety and health, including the psychological factors involved, and by developing innovative methods, techniques, and approaches for dealing with occupational safety and health problems ; (6) by exploring ways to discover latent diseases, establishing causal connections between diseases and work in environmental conditions, and conducting other research relating to health prob- lems, in recognition of the fact that occupational health standards present problems often different from those involved in occupa- tional safety; (7) by providing medical criteria which will assure insofar as practicable that no employee will suffer diminished health, func- tional capacity, or life expectancy as a result of his work experience ; (8) b",
  "url": "https://archive.org/details/cia-readingroom-document-cia-rdp87b01034r000200100035-5",
  "timestamp": "2026-03-06T04:18:02.169612",
  "tongue_coords": [
    0.0,
    0.0,
    0.0,
    0.0,
    0.0,
    0.0
  ],
  "trust_score": 0.5,
  "governance_zone": "YELLOW",
  "chain_hash": "466a4d7f2af612ec7dd632a4f3433151cb0ba41f06fba2cdd41b4d9315e651d3",
  "parent_hash": "764119b649ad7ce31b4df93267d7b6ea09c754c8e7807ffe7bdaa7d5ee9ce98e",
  "metadata": {
    "ia_identifier": "cia-readingroom-document-cia-rdp87b01034r000200100035-5",
    "media_type": "texts",
    "downloads": 83,
    "subjects": [
      "CIA Reading Room"
    ]
  }
}